simplebuilder/__init__.py
simplebuilder/__main__.py
simplebuilder-0.4.0.dist-info/METADATA
simplebuilder-0.4.0.dist-info/WHEEL
simplebuilder-0.4.0.dist-info/entry_points.txt
simplebuilder-0.4.0.dist-info/RECORD
